miscgeom-0.0.2.dist-info/METADATA
miscgeom-0.0.2.dist-info/WHEEL
miscgeom-0.0.2.dist-info/LICENSE.txt
miscgeom/intersection/fast_intersection.cp312-win_amd64.pyd
miscgeom/intersection/fast_intersection.cp312-win_amd64.dll.a
miscgeom/intersection/__init__.py
miscgeom/intersection/_intersection.py
miscgeom/intersection/tests/test_intersection.py
miscgeom-0.0.2.dist-info/RECORD
