Metadata-Version: 2.1
Name: miscgeom
Version: 0.0.2
Summary: Python library containing miscellaneous geometry computing routines.
Author-Email: Spencer Bertram <spenbert02@gmail.com>
License:                     GNU GENERAL PUBLIC LICENSE
Requires-Python: >=3.12
Requires-Dist: numpy>=2.0.0
Provides-Extra: dev
Requires-Dist: fury; extra == "dev"
Requires-Dist: pytest; extra == "dev"
